modulairy_redirect_app/__init__.py
modulairy_redirect_app-0.0.16.dist-info/METADATA
modulairy_redirect_app-0.0.16.dist-info/WHEEL
modulairy_redirect_app-0.0.16.dist-info/top_level.txt
modulairy_redirect_app-0.0.16.dist-info/RECORD
