Metadata-Version: 2.1
Name: modulairy-redirect-app
Version: 0.0.16
Summary: Modulairy Redirect App is a flexible Flask-based redirection application that dynamically redirects incoming HTTP requests based on environment variables prefixed with TARGET_.
Home-page: https://github.com/modulairy/modulairy-redirect-app
Author: Fatih Mehmet ARSLAN
Author-email: contact@fmarslan.com
License: MIT
Classifier: Development Status :: 4 - Beta
Classifier: Intended Audience :: Developers
Classifier: License :: OSI Approved :: MIT License
Classifier: Programming Language :: Python :: 3
Classifier: Programming Language :: Python :: 3.6
Classifier: Programming Language :: Python :: 3.7
Classifier: Programming Language :: Python :: 3.8
Classifier: Programming Language :: Python :: 3.9
Requires-Dist: Flask
Requires-Dist: gunicorn
